himpunan_tim5/__init__.py
himpunan_tim5/main.py
himpunan_tim5-0.1.3.dist-info/METADATA
himpunan_tim5-0.1.3.dist-info/WHEEL
himpunan_tim5-0.1.3.dist-info/top_level.txt
himpunan_tim5-0.1.3.dist-info/RECORD
