Metadata-Version: 2.1
Name: himpunan_tim5
Version: 0.1.3
Summary: Library Python untuk implementasi teori himpunan
Author: Deny Wahyudi Asaloei
